test/__init__.py
test/test_canvas.py
test/test_simple_graph.py
test/test_window.py
tkinterx/__init__.py
tkinterx/graph_utils.py
tkinterx/image_utils.py
tkinterx/meta.py
tkinterx/param.py
tkinterx/utils.py
tkinterx/window.py
tkinterx/graph/__init__.py
tkinterx/graph/canvas.py
tkinterx/graph/canvas_design.py
tkinterx/graph/drawing.py
tkinterx/graph/generate_label.py
tkinterx/graph/shape.py
tkinterx/tools/__init__.py
tkinterx/tools/colors.py
tkinterx/tools/constant.py
tkinterx/tools/helper.py
tkinterx/tools/utils.py
tkinterx-0.0.9.dist-info/LICENSE
tkinterx-0.0.9.dist-info/METADATA
tkinterx-0.0.9.dist-info/WHEEL
tkinterx-0.0.9.dist-info/top_level.txt
tkinterx-0.0.9.dist-info/RECORD
